setup.py
roshan_dist_pack/Binomialdistribution.py
roshan_dist_pack/Gaussiandistribution.py
roshan_dist_pack/Generaldistribution.py
roshan_dist_pack/__init__.py
roshan_dist_pack.egg-info/PKG-INFO
roshan_dist_pack.egg-info/SOURCES.txt
roshan_dist_pack.egg-info/dependency_links.txt
roshan_dist_pack.egg-info/not-zip-safe
roshan_dist_pack.egg-info/top_level.txt