Metadata-Version: 1.0
Name: roshan-dist-pack
Version: 1.2
Summary: Gaussian and Binomial distributions
Home-page: UNKNOWN
Author: UNKNOWN
Author-email: roshanbisht1992@gmail.com
License: UNKNOWN
Platform: UNKNOWN
